{
  "listItems": [
    {
      "ticketnumber": "IND-JOB#-000000001",
      "problemcategory": "Screen",
      "firstname": "Ram",
      "lastname": "Chauhan",
      "pickupaddress": "Pune",
      "mobilenumber": "89812345"
    },
    {
      "ticketnumber": "IND-JOB#-000000002",
       "problemcategory": "Screen",
      "firstname": "Gaurav",
      "lastname": "Navale",
      "pickupaddress": "Nashik",
      "mobilenumber": "9345567856"
    },
    {
      "ticketnumber": "IND-JOB#-000000003",
       "problemcategory": "Screen",
      "firstname": "Ravi",
      "lastname": "Patil",
      "pickupaddress": "Mumbai",
      "mobilenumber": "9123456789"
    }
  ],
  "selectTabs": [
    {
      "$i": 0,
      "tabName": "Repair Job"
    },
    {
      "$i": 1,
      "tabName": "Service Job",
      "isSelected": true
    }
  ],
  "isservicejob": true
}
